mcp_server_hai/__init__.py
mcp_server_hai/api_driver.py
mcp_server_hai/bundle_type.csv
mcp_server_hai/server.py
mcp_server_hai-1.2.6.dist-info/METADATA
mcp_server_hai-1.2.6.dist-info/WHEEL
mcp_server_hai-1.2.6.dist-info/entry_points.txt
mcp_server_hai-1.2.6.dist-info/top_level.txt
mcp_server_hai-1.2.6.dist-info/RECORD
