Metadata-Version: 2.4
Name: mcp-server-hai
Version: 1.2.6
Summary: A MCP server implementation for HAI (Hyper Application Inventor) services
Requires-Python: >=3.12
Requires-Dist: build>=1.2.2.post1
Requires-Dist: fastmcp>=2.12.2
Requires-Dist: mcp[cli]>=1.6.0
Requires-Dist: tencentcloud-sdk-python-hai>=3.0.1357
Requires-Dist: twine>=6.1.0
Requires-Dist: uvicorn>=0.34.0
